Workbook

Sheet Lisez-moi
B2: Suivi Budget, classeur d'échange
B3: Exporté le 29 septembre 2026. Ce fichier contient toutes tes données, comme dans l'application. Tu peux le remplir sans connexion, puis le réimporter : Réglages, Importer un fichier Excel.
B5: Les onglets
B6: • Réglages : le solde initial, avant le premier mois.
B7: • Catégories : la liste des catégories (la catégorie « Épargne » pilote le calcul de l'épargne).
B8: • Dépenses fixes : le modèle des charges récurrentes, copié dans chaque mois par le bouton « Ajouter les dépenses fixes ».
B9: • Mois : un mois par ligne, avec les soldes calculés (colonnes grises).
B10: • Transactions : toutes les lignes de tous les mois (revenus, dépenses fixes, dépenses variables).
B12: Comment remplir
B13: • Ajoute une ligne à la suite du tableau. Laisse la colonne ID vide (elle est masquée) : l'application la créera.
B14: • Ne supprime pas la colonne ID et ne modifie pas les identifiants existants : ils permettent de retrouver chaque ligne.
B15: • Écris le mois au format AAAA-MM (par exemple 2026-10), ou choisis-le dans la liste.
... B28: Suivi Budget, classeur v1

Sheet Réglages
A1: Réglage | B1: Valeur
A2: Solde initial (€) | B2: 1000 | C2: Le solde bancaire avant le premier mois enregistré.
A3: Catégorie d'épargne | B3: Épargne | C3: Nom de la catégorie d'épargne, utilisé par les formules de l'onglet Mois (ne pas modifier).

Sheet Catégories
A1: Nom
A2: Logement
A3: Abonnements
A4: Courses
A5: Transport
A6: Épargne

Sheet Dépenses fixes
A1: ID | B1: Nom | C1: Montant de la période (€) | D1: Catégorie | E1: Fréquence | F1: Jour de prélèvement | G1: Active | H1: Part mensuelle (€)
A2: f1 | B2: Loyer | C2: 520 | D2: Logement | E2: Mensuelle | F2: 3 | G2: Oui | H2: =IF(OR($B2="",$C2=""),"",ROUND($C2/CHOOSE(MATCH($E2,{"Mensuelle","Tous les 2 mois","Trimestrielle","Semestrielle","Annuelle"},0),1,2,3,6,12),2)) -> 520
A3: f2 | B3: Assurance auto | C3: 480 | D3: Transport | E3: Annuelle | F3: 15 | G3: Oui | H3: =IF(OR($B3="",$C3=""),"",ROUND($C3/CHOOSE(MATCH($E3,{"Mensuelle","Tous les 2 mois","Trimestrielle","Semestrielle","Annuelle"},0),1,2,3,6,12),2)) -> 40
A4: f3 | B4: Cantine | C4: 30 | D4: Courses | E4: Trimestrielle | F4: 1 | G4: Non | H4: =IF(OR($B4="",$C4=""),"",ROUND($C4/CHOOSE(MATCH($E4,{"Mensuelle","Tous les 2 mois","Trimestrielle","Semestrielle","Annuelle"},0),1,2,3,6,12),2)) -> 10
H5: =IF(OR($B5="",$C5=""),"",ROUND($C5/CHOOSE(MATCH($E5,{"Mensuelle","Tous les 2 mois","Trimestrielle","Semestrielle","Annuelle"},0),1,2,3,6,12),2))
H6: =IF(OR($B6="",$C6=""),"",ROUND($C6/CHOOSE(MATCH($E6,{"Mensuelle","Tous les 2 mois","Trimestrielle","Semestrielle","Annuelle"},0),1,2,3,6,12),2))
H7: =IF(OR($B7="",$C7=""),"",ROUND($C7/CHOOSE(MATCH($E7,{"Mensuelle","Tous les 2 mois","Trimestrielle","Semestrielle","Annuelle"},0),1,2,3,6,12),2))
H8: =IF(OR($B8="",$C8=""),"",ROUND($C8/CHOOSE(MATCH($E8,{"Mensuelle","Tous les 2 mois","Trimestrielle","Semestrielle","Annuelle"},0),1,2,3,6,12),2))
H9: =IF(OR($B9="",$C9=""),"",ROUND($C9/CHOOSE(MATCH($E9,{"Mensuelle","Tous les 2 mois","Trimestrielle","Semestrielle","Annuelle"},0),1,2,3,6,12),2))
H10: =IF(OR($B10="",$C10=""),"",ROUND($C10/CHOOSE(MATCH($E10,{"Mensuelle","Tous les 2 mois","Trimestrielle","Semestrielle","Annuelle"},0),1,2,3,6,12),2))
H11: =IF(OR($B11="",$C11=""),"",ROUND($C11/CHOOSE(MATCH($E11,{"Mensuelle","Tous les 2 mois","Trimestrielle","Semestrielle","Annuelle"},0),1,2,3,6,12),2))
H12: =IF(OR($B12="",$C12=""),"",ROUND($C12/CHOOSE(MATCH($E12,{"Mensuelle","Tous les 2 mois","Trimestrielle","Semestrielle","Annuelle"},0),1,2,3,6,12),2))
H13: =IF(OR($B13="",$C13=""),"",ROUND($C13/CHOOSE(MATCH($E13,{"Mensuelle","Tous les 2 mois","Trimestrielle","Semestrielle","Annuelle"},0),1,2,3,6,12),2))
H14: =IF(OR($B14="",$C14=""),"",ROUND($C14/CHOOSE(MATCH($E14,{"Mensuelle","Tous les 2 mois","Trimestrielle","Semestrielle","Annuelle"},0),1,2,3,6,12),2))
H15: =IF(OR($B15="",$C15=""),"",ROUND($C15/CHOOSE(MATCH($E15,{"Mensuelle","Tous les 2 mois","Trimestrielle","Semestrielle","Annuelle"},0),1,2,3,6,12),2))
H16: =IF(OR($B16="",$C16=""),"",ROUND($C16/CHOOSE(MATCH($E16,{"Mensuelle","Tous les 2 mois","Trimestrielle","Semestrielle","Annuelle"},0),1,2,3,6,12),2))
... H304: =IF(OR($B304="",$C304=""),"",ROUND($C304/CHOOSE(MATCH($E304,{"Mensuelle","Tous les 2 mois","Trimestrielle","Semestrielle","Annuelle"},0),1,2,3,6,12),2))

Sheet Mois
A1: ID | B1: Mois (AAAA-MM) | C1: Statut | D1: Solde de départ forcé (€) | E1: Solde réel constaté (€) | F1: Solde début (€) | G1: Revenus (€) | H1: Dépenses hors épargne (€) | I1: Épargne (€) | J1: Taux d'épargne | K1: Évolution du compte (€) | L1: Solde théorique fin de mois (€)
A2: m1 | B2: 2026-08 | C2: Clôturé | F2: =IF($B2="","",IF($D2<>"",$D2,N('Réglages'!$B$2))) -> 1000 | G2: =IF($B2="","",SUMPRODUCT(--('Transactions'!$B$2:$B$5000=$B2),--('Transactions'!$C$2:$C$5000="Revenu"),'Transactions'!$E$2:$E$5000)) -> 2000 | H2: =IF($B2="","",SUMPRODUCT(--('Transactions'!$B$2:$B$5000=$B2),--('Transactions'!$C$2:$C$5000<>"Revenu"),--('Transactions'!$F$2:$F$5000<>'Réglages'!$B$3),'Transactions'!$E$2:$E$5000)) -> 670.5 | I2: =IF($B2="","",SUMPRODUCT(--('Transactions'!$B$2:$B$5000=$B2),--('Transactions'!$F$2:$F$5000='Réglages'!$B$3),'Transactions'!$E$2:$E$5000)) -> 200 | J2: =IF($B2="","",IF($G2>0,$I2/$G2,0)) -> 0.1 | K2: =IF($B2="","",$G2-$H2-$I2) -> 1129.5 | L2: =IF($B2="","",$F2+$K2) -> 2129.5
A3: m2 | B3: 2026-09 | C3: Courant | E3: 1234.5 | F3: =IF($B3="","",IF($D3<>"",$D3,N($L2))) -> 2129.5 | G3: =IF($B3="","",SUMPRODUCT(--('Transactions'!$B$2:$B$5000=$B3),--('Transactions'!$C$2:$C$5000="Revenu"),'Transactions'!$E$2:$E$5000)) -> 2000 | H3: =IF($B3="","",SUMPRODUCT(--('Transactions'!$B$2:$B$5000=$B3),--('Transactions'!$C$2:$C$5000<>"Revenu"),--('Transactions'!$F$2:$F$5000<>'Réglages'!$B$3),'Transactions'!$E$2:$E$5000)) -> 558.2 | I3: =IF($B3="","",SUMPRODUCT(--('Transactions'!$B$2:$B$5000=$B3),--('Transactions'!$F$2:$F$5000='Réglages'!$B$3),'Transactions'!$E$2:$E$5000)) -> 200 | J3: =IF($B3="","",IF($G3>0,$I3/$G3,0)) -> 0.1 | K3: =IF($B3="","",$G3-$H3-$I3) -> 1241.8 | L3: =IF($B3="","",$F3+$K3) -> 3371.3
F4: =IF($B4="","",IF($D4<>"",$D4,N($L3))) | G4: =IF($B4="","",SUMPRODUCT(--('Transactions'!$B$2:$B$5000=$B4),--('Transactions'!$C$2:$C$5000="Revenu"),'Transactions'!$E$2:$E$5000)) | H4: =IF($B4="","",SUMPRODUCT(--('Transactions'!$B$2:$B$5000=$B4),--('Transactions'!$C$2:$C$5000<>"Revenu"),--('Transactions'!$F$2:$F$5000<>'Réglages'!$B$3),'Transactions'!$E$2:$E$5000)) | I4: =IF($B4="","",SUMPRODUCT(--('Transactions'!$B$2:$B$5000=$B4),--('Transactions'!$F$2:$F$5000='Réglages'!$B$3),'Transactions'!$E$2:$E$5000)) | J4: =IF($B4="","",IF($G4>0,$I4/$G4,0)) | K4: =IF($B4="","",$G4-$H4-$I4) | L4: =IF($B4="","",$F4+$K4)
F5: =IF($B5="","",IF($D5<>"",$D5,N($L4))) | G5: =IF($B5="","",SUMPRODUCT(--('Transactions'!$B$2:$B$5000=$B5),--('Transactions'!$C$2:$C$5000="Revenu"),'Transactions'!$E$2:$E$5000)) | H5: =IF($B5="","",SUMPRODUCT(--('Transactions'!$B$2:$B$5000=$B5),--('Transactions'!$C$2:$C$5000<>"Revenu"),--('Transactions'!$F$2:$F$5000<>'Réglages'!$B$3),'Transactions'!$E$2:$E$5000)) | I5: =IF($B5="","",SUMPRODUCT(--('Transactions'!$B$2:$B$5000=$B5),--('Transactions'!$F$2:$F$5000='Réglages'!$B$3),'Transactions'!$E$2:$E$5000)) | J5: =IF($B5="","",IF($G5>0,$I5/$G5,0)) | K5: =IF($B5="","",$G5-$H5-$I5) | L5: =IF($B5="","",$F5+$K5)
F6: =IF($B6="","",IF($D6<>"",$D6,N($L5))) | G6: =IF($B6="","",SUMPRODUCT(--('Transactions'!$B$2:$B$5000=$B6),--('Transactions'!$C$2:$C$5000="Revenu"),'Transactions'!$E$2:$E$5000)) | H6: =IF($B6="","",SUMPRODUCT(--('Transactions'!$B$2:$B$5000=$B6),--('Transactions'!$C$2:$C$5000<>"Revenu"),--('Transactions'!$F$2:$F$5000<>'Réglages'!$B$3),'Transactions'!$E$2:$E$5000)) | I6: =IF($B6="","",SUMPRODUCT(--('Transactions'!$B$2:$B$5000=$B6),--('Transactions'!$F$2:$F$5000='Réglages'!$B$3),'Transactions'!$E$2:$E$5000)) | J6: =IF($B6="","",IF($G6>0,$I6/$G6,0)) | K6: =IF($B6="","",$G6-$H6-$I6) | L6: =IF($B6="","",$F6+$K6)
F7: =IF($B7="","",IF($D7<>"",$D7,N($L6))) | G7: =IF($B7="","",SUMPRODUCT(--('Transactions'!$B$2:$B$5000=$B7),--('Transactions'!$C$2:$C$5000="Revenu"),'Transactions'!$E$2:$E$5000)) | H7: =IF($B7="","",SUMPRODUCT(--('Transactions'!$B$2:$B$5000=$B7),--('Transactions'!$C$2:$C$5000<>"Revenu"),--('Transactions'!$F$2:$F$5000<>'Réglages'!$B$3),'Transactions'!$E$2:$E$5000)) | I7: =IF($B7="","",SUMPRODUCT(--('Transactions'!$B$2:$B$5000=$B7),--('Transactions'!$F$2:$F$5000='Réglages'!$B$3),'Transactions'!$E$2:$E$5000)) | J7: =IF($B7="","",IF($G7>0,$I7/$G7,0)) | K7: =IF($B7="","",$G7-$H7-$I7) | L7: =IF($B7="","",$F7+$K7)
F8: =IF($B8="","",IF($D8<>"",$D8,N($L7))) | G8: =IF($B8="","",SUMPRODUCT(--('Transactions'!$B$2:$B$5000=$B8),--('Transactions'!$C$2:$C$5000="Revenu"),'Transactions'!$E$2:$E$5000)) | H8: =IF($B8="","",SUMPRODUCT(--('Transactions'!$B$2:$B$5000=$B8),--('Transactions'!$C$2:$C$5000<>"Revenu"),--('Transactions'!$F$2:$F$5000<>'Réglages'!$B$3),'Transactions'!$E$2:$E$5000)) | I8: =IF($B8="","",SUMPRODUCT(--('Transactions'!$B$2:$B$5000=$B8),--('Transactions'!$F$2:$F$5000='Réglages'!$B$3),'Transactions'!$E$2:$E$5000)) | J8: =IF($B8="","",IF($G8>0,$I8/$G8,0)) | K8: =IF($B8="","",$G8-$H8-$I8) | L8: =IF($B8="","",$F8+$K8)
F9: =IF($B9="","",IF($D9<>"",$D9,N($L8))) | G9: =IF($B9="","",SUMPRODUCT(--('Transactions'!$B$2:$B$5000=$B9),--('Transactions'!$C$2:$C$5000="Revenu"),'Transactions'!$E$2:$E$5000)) | H9: =IF($B9="","",SUMPRODUCT(--('Transactions'!$B$2:$B$5000=$B9),--('Transactions'!$C$2:$C$5000<>"Revenu"),--('Transactions'!$F$2:$F$5000<>'Réglages'!$B$3),'Transactions'!$E$2:$E$5000)) | I9: =IF($B9="","",SUMPRODUCT(--('Transactions'!$B$2:$B$5000=$B9),--('Transactions'!$F$2:$F$5000='Réglages'!$B$3),'Transactions'!$E$2:$E$5000)) | J9: =IF($B9="","",IF($G9>0,$I9/$G9,0)) | K9: =IF($B9="","",$G9-$H9-$I9) | L9: =IF($B9="","",$F9+$K9)
F10: =IF($B10="","",IF($D10<>"",$D10,N($L9))) | G10: =IF($B10="","",SUMPRODUCT(--('Transactions'!$B$2:$B$5000=$B10),--('Transactions'!$C$2:$C$5000="Revenu"),'Transactions'!$E$2:$E$5000)) | H10: =IF($B10="","",SUMPRODUCT(--('Transactions'!$B$2:$B$5000=$B10),--('Transactions'!$C$2:$C$5000<>"Revenu"),--('Transactions'!$F$2:$F$5000<>'Réglages'!$B$3),'Transactions'!$E$2:$E$5000)) | I10: =IF($B10="","",SUMPRODUCT(--('Transactions'!$B$2:$B$5000=$B10),--('Transactions'!$F$2:$F$5000='Réglages'!$B$3),'Transactions'!$E$2:$E$5000)) | J10: =IF($B10="","",IF($G10>0,$I10/$G10,0)) | K10: =IF($B10="","",$G10-$H10-$I10) | L10: =IF($B10="","",$F10+$K10)
F11: =IF($B11="","",IF($D11<>"",$D11,N($L10))) | G11: =IF($B11="","",SUMPRODUCT(--('Transactions'!$B$2:$B$5000=$B11),--('Transactions'!$C$2:$C$5000="Revenu"),'Transactions'!$E$2:$E$5000)) | H11: =IF($B11="","",SUMPRODUCT(--('Transactions'!$B$2:$B$5000=$B11),--('Transactions'!$C$2:$C$5000<>"Revenu"),--('Transactions'!$F$2:$F$5000<>'Réglages'!$B$3),'Transactions'!$E$2:$E$5000)) | I11: =IF($B11="","",SUMPRODUCT(--('Transactions'!$B$2:$B$5000=$B11),--('Transactions'!$F$2:$F$5000='Réglages'!$B$3),'Transactions'!$E$2:$E$5000)) | J11: =IF($B11="","",IF($G11>0,$I11/$G11,0)) | K11: =IF($B11="","",$G11-$H11-$I11) | L11: =IF($B11="","",$F11+$K11)
F12: =IF($B12="","",IF($D12<>"",$D12,N($L11))) | G12: =IF($B12="","",SUMPRODUCT(--('Transactions'!$B$2:$B$5000=$B12),--('Transactions'!$C$2:$C$5000="Revenu"),'Transactions'!$E$2:$E$5000)) | H12: =IF($B12="","",SUMPRODUCT(--('Transactions'!$B$2:$B$5000=$B12),--('Transactions'!$C$2:$C$5000<>"Revenu"),--('Transactions'!$F$2:$F$5000<>'Réglages'!$B$3),'Transactions'!$E$2:$E$5000)) | I12: =IF($B12="","",SUMPRODUCT(--('Transactions'!$B$2:$B$5000=$B12),--('Transactions'!$F$2:$F$5000='Réglages'!$B$3),'Transactions'!$E$2:$E$5000)) | J12: =IF($B12="","",IF($G12>0,$I12/$G12,0)) | K12: =IF($B12="","",$G12-$H12-$I12) | L12: =IF($B12="","",$F12+$K12)
F13: =IF($B13="","",IF($D13<>"",$D13,N($L12))) | G13: =IF($B13="","",SUMPRODUCT(--('Transactions'!$B$2:$B$5000=$B13),--('Transactions'!$C$2:$C$5000="Revenu"),'Transactions'!$E$2:$E$5000)) | H13: =IF($B13="","",SUMPRODUCT(--('Transactions'!$B$2:$B$5000=$B13),--('Transactions'!$C$2:$C$5000<>"Revenu"),--('Transactions'!$F$2:$F$5000<>'Réglages'!$B$3),'Transactions'!$E$2:$E$5000)) | I13: =IF($B13="","",SUMPRODUCT(--('Transactions'!$B$2:$B$5000=$B13),--('Transactions'!$F$2:$F$5000='Réglages'!$B$3),'Transactions'!$E$2:$E$5000)) | J13: =IF($B13="","",IF($G13>0,$I13/$G13,0)) | K13: =IF($B13="","",$G13-$H13-$I13) | L13: =IF($B13="","",$F13+$K13)
F14: =IF($B14="","",IF($D14<>"",$D14,N($L13))) | G14: =IF($B14="","",SUMPRODUCT(--('Transactions'!$B$2:$B$5000=$B14),--('Transactions'!$C$2:$C$5000="Revenu"),'Transactions'!$E$2:$E$5000)) | H14: =IF($B14="","",SUMPRODUCT(--('Transactions'!$B$2:$B$5000=$B14),--('Transactions'!$C$2:$C$5000<>"Revenu"),--('Transactions'!$F$2:$F$5000<>'Réglages'!$B$3),'Transactions'!$E$2:$E$5000)) | I14: =IF($B14="","",SUMPRODUCT(--('Transactions'!$B$2:$B$5000=$B14),--('Transactions'!$F$2:$F$5000='Réglages'!$B$3),'Transactions'!$E$2:$E$5000)) | J14: =IF($B14="","",IF($G14>0,$I14/$G14,0)) | K14: =IF($B14="","",$G14-$H14-$I14) | L14: =IF($B14="","",$F14+$K14)
F15: =IF($B15="","",IF($D15<>"",$D15,N($L14))) | G15: =IF($B15="","",SUMPRODUCT(--('Transactions'!$B$2:$B$5000=$B15),--('Transactions'!$C$2:$C$5000="Revenu"),'Transactions'!$E$2:$E$5000)) | H15: =IF($B15="","",SUMPRODUCT(--('Transactions'!$B$2:$B$5000=$B15),--('Transactions'!$C$2:$C$5000<>"Revenu"),--('Transactions'!$F$2:$F$5000<>'Réglages'!$B$3),'Transactions'!$E$2:$E$5000)) | I15: =IF($B15="","",SUMPRODUCT(--('Transactions'!$B$2:$B$5000=$B15),--('Transactions'!$F$2:$F$5000='Réglages'!$B$3),'Transactions'!$E$2:$E$5000)) | J15: =IF($B15="","",IF($G15>0,$I15/$G15,0)) | K15: =IF($B15="","",$G15-$H15-$I15) | L15: =IF($B15="","",$F15+$K15)
... F61: =IF($B61="","",IF($D61<>"",$D61,N($L60))) | G61: =IF($B61="","",SUMPRODUCT(--('Transactions'!$B$2:$B$5000=$B61),--('Transactions'!$C$2:$C$5000="Revenu"),'Transactions'!$E$2:$E$5000)) | H61: =IF($B61="","",SUMPRODUCT(--('Transactions'!$B$2:$B$5000=$B61),--('Transactions'!$C$2:$C$5000<>"Revenu"),--('Transactions'!$F$2:$F$5000<>'Réglages'!$B$3),'Transactions'!$E$2:$E$5000)) | I61: =IF($B61="","",SUMPRODUCT(--('Transactions'!$B$2:$B$5000=$B61),--('Transactions'!$F$2:$F$5000='Réglages'!$B$3),'Transactions'!$E$2:$E$5000)) | J61: =IF($B61="","",IF($G61>0,$I61/$G61,0)) | K61: =IF($B61="","",$G61-$H61-$I61) | L61: =IF($B61="","",$F61+$K61)

Sheet Transactions
A1: ID | B1: Mois (AAAA-MM) | C1: Type | D1: Nom | E1: Montant (€) | F1: Catégorie | G1: Date | H1: Détail | I1: Nécessaire ? | J1: Reçu ?
A2: t1 | B2: 2026-08 | C2: Revenu | D2: Salaire août | E2: 2000 | G2: 46235 | J2: Oui
A3: t2 | B3: 2026-08 | C3: Dépense fixe | D3: Loyer | E3: 520 | F3: Logement | G3: 46237 | I3: Oui
A4: t3 | B4: 2026-08 | C4: Dépense fixe | D4: Virement épargne | E4: 200 | F4: Épargne | G4: 46244 | I4: Oui
A5: t4 | B5: 2026-08 | C5: Dépense variable | D5: Courses | E5: 150.5 | F5: Courses | G5: 46246 | H5: Carrefour | I5: Non
A6: t8 | B6: 2026-09 | C6: Dépense variable | D6: Transport | E6: 38.2 | F6: Transport | I6: Oui
A7: t5 | B7: 2026-09 | C7: Revenu | D7: Salaire sept | E7: 2000 | G7: 46266 | J7: Non
A8: t6 | B8: 2026-09 | C8: Dépense fixe | D8: Loyer | E8: 520 | F8: Logement | G8: 46268 | I8: Oui
A9: t7 | B9: 2026-09 | C9: Dépense fixe | D9: Virement épargne | E9: 200 | F9: Épargne | G9: 46275 | I9: Oui
